JWTs/JWT_tapo44ek.py
JWTs/__init__.py
JWT_tapo44ek-1.0.6.dist-info/LICENSE
JWT_tapo44ek-1.0.6.dist-info/METADATA
JWT_tapo44ek-1.0.6.dist-info/WHEEL
JWT_tapo44ek-1.0.6.dist-info/top_level.txt
JWT_tapo44ek-1.0.6.dist-info/RECORD
