Metadata-Version: 2.2
Name: JWT_tapo44ek
Version: 1.0.6
Summary: A simple library for JWT management with FastAPI
Author-email: "Viktor Arsenev (GitHub tapo44ek)" <viktooooor2001@gmail.com>, "Alexander Andreev (GitHub tzinchy)" <dreevxq@gmail.com>
License: MIT
Classifier: Programming Language :: Python :: 3
Classifier: Framework :: FastAPI
Classifier: License :: OSI Approved :: MIT License
Classifier: Operating System :: OS Independent
Requires-Python: >=3.8
License-File: LICENSE
Requires-Dist: PyJWT>=2.6.0
Requires-Dist: fastapi>=0.95.0
